{
  "overrides": [
    {
      "predicate": {
        "refinedstorage:color": 0.0
      },
      "model": "refinedstorage:item/crafter_manager/white"
    },
    {
      "predicate": {
        "refinedstorage:color": 1.0
      },
      "model": "refinedstorage:item/crafter_manager/orange"
    },
    {
      "predicate": {
        "refinedstorage:color": 2.0
      },
      "model": "refinedstorage:item/crafter_manager/magenta"
    },
    {
      "predicate": {
        "refinedstorage:color": 3.0
      },
      "model": "refinedstorage:item/crafter_manager/light_blue"
    },
    {
      "predicate": {
        "refinedstorage:color": 4.0
      },
      "model": "refinedstorage:item/crafter_manager/yellow"
    },
    {
      "predicate": {
        "refinedstorage:color": 5.0
      },
      "model": "refinedstorage:item/crafter_manager/lime"
    },
    {
      "predicate": {
        "refinedstorage:color": 6.0
      },
      "model": "refinedstorage:item/crafter_manager/pink"
    },
    {
      "predicate": {
        "refinedstorage:color": 7.0
      },
      "model": "refinedstorage:item/crafter_manager/gray"
    },
    {
      "predicate": {
        "refinedstorage:color": 8.0
      },
      "model": "refinedstorage:item/crafter_manager/light_gray"
    },
    {
      "predicate": {
        "refinedstorage:color": 9.0
      },
      "model": "refinedstorage:item/crafter_manager/cyan"
    },
    {
      "predicate": {
        "refinedstorage:color": 10.0
      },
      "model": "refinedstorage:item/crafter_manager/purple"
    },
    {
      "predicate": {
        "refinedstorage:color": 11.0
      },
      "model": "refinedstorage:item/crafter_manager/blue"
    },
    {
      "predicate": {
        "refinedstorage:color": 12.0
      },
      "model": "refinedstorage:item/crafter_manager/brown"
    },
    {
      "predicate": {
        "refinedstorage:color": 13.0
      },
      "model": "refinedstorage:item/crafter_manager/green"
    },
    {
      "predicate": {
        "refinedstorage:color": 14.0
      },
      "model": "refinedstorage:item/crafter_manager/red"
    },
    {
      "predicate": {
        "refinedstorage:color": 15.0
      },
      "model": "refinedstorage:item/crafter_manager/black"
    }
  ]
}